denvr/__about__.py
denvr/__init__.py
denvr/auth.py
denvr/client.py
denvr/config.py
denvr/session.py
denvr/utils.py
denvr/validate.py
denvr/waiters.py
denvr/api/__init__.py
denvr/api/v1/__init__.py
denvr/api/v1/clusters.py
denvr/api/v1/servers/__init__.py
denvr/api/v1/servers/applications.py
denvr/api/v1/servers/images.py
denvr/api/v1/servers/metal.py
denvr/api/v1/servers/virtual.py
denvr-0.5.0.dist-info/METADATA
denvr-0.5.0.dist-info/WHEEL
denvr-0.5.0.dist-info/licenses/LICENSE.txt
denvr-0.5.0.dist-info/RECORD
