Metadata-Version: 2.4
Name: denvr
Version: 0.5.0
Summary: Python SDK for the Denvr Cloud API
Project-URL: Documentation, https://github.com/denvrdata/denvrpy#readme
Project-URL: Issues, https://github.com/denvrdata/denvrpy/issues
Project-URL: Source, https://github.com/denvrdata/denvrpy
Author-email: rofinn <rory@denvrdata.com>
License-Expression: MIT
License-File: LICENSE.txt
Classifier: Development Status :: 4 - Beta
Classifier: Programming Language :: Python
Classifier: Programming Language :: Python :: 3.8
Classifier: Programming Language :: Python :: 3.9
Classifier: Programming Language :: Python :: 3.10
Classifier: Programming Language :: Python :: 3.11
Classifier: Programming Language :: Python :: 3.12
Classifier: Programming Language :: Python :: 3.13
Classifier: Programming Language :: Python :: Implementation :: CPython
Classifier: Programming Language :: Python :: Implementation :: PyPy
Requires-Python: >=3.8
Requires-Dist: requests>=2.27
Requires-Dist: toml~=0.10
Requires-Dist: urllib3>=2.2.3
